prijsoog/__init__.py
prijsoog/_base.py
prijsoog/supermarkets/__init__.py
prijsoog/supermarkets/ah.py
prijsoog/supermarkets/jumbo.py
prijsoog-0.1.7.dist-info/AUTHORS.rst
prijsoog-0.1.7.dist-info/LICENSE
prijsoog-0.1.7.dist-info/METADATA
prijsoog-0.1.7.dist-info/WHEEL
prijsoog-0.1.7.dist-info/top_level.txt
prijsoog-0.1.7.dist-info/RECORD
