Metadata-Version: 2.1
Name: prijsoog
Version: 0.1.7
Summary: Prijsoog compares prices for items in Dutch grocery stores.
Home-page: https://github.com/PepijnBoers/prijsoog
Author: Pepijn Boers
Author-email: pepijnbb@gmail.com
License: MIT license
Keywords: prijsoog
Platform: UNKNOWN
Classifier: Development Status :: 2 - Pre-Alpha
Classifier: Intended Audience :: Developers
Classifier: License :: OSI Approved :: MIT License
Classifier: Natural Language :: English
Classifier: Programming Language :: Python :: 3
Classifier: Programming Language :: Python :: 3.6
Classifier: Programming Language :: Python :: 3.7
Classifier: Programming Language :: Python :: 3.8
Requires-Python: >=3.6
License-File: LICENSE
License-File: AUTHORS.rst
Requires-Dist: pytest
Requires-Dist: requests
Requires-Dist: beautifulsoup4
Requires-Dist: pytest-cov
Requires-Dist: wheel
